gcode_thumbnail_tool.py
gcode_thumbnail_tool-0.1.2.dist-info/licenses/LICENSE.txt
gcode_thumbnail_tool-0.1.2.dist-info/METADATA
gcode_thumbnail_tool-0.1.2.dist-info/WHEEL
gcode_thumbnail_tool-0.1.2.dist-info/entry_points.txt
gcode_thumbnail_tool-0.1.2.dist-info/top_level.txt
gcode_thumbnail_tool-0.1.2.dist-info/RECORD
