Metadata-Version: 2.4
Name: gcode-thumbnail-tool
Version: 0.1.2
Summary: A small tool to analyse and extract thumbnails rendered into GCODE files
Author-email: Gina Häußge <gina@octoprint.org>, jneilliii <jneilliii+github@gmail.com>
Maintainer-email: Gina Häußge <gina@octoprint.org>
License-Expression: AGPL-3.0-or-later
Project-URL: homepage, https://github.com/OctoPrint/gcode-thumbnail-tool/
Project-URL: issues, https://github.com/OctoPrint/gcode-thumbnail-tool/issues
Project-URL: source, https://github.com/OctoPrint/gcode-thumbnail-tool/
Requires-Python: >=3.9
License-File: LICENSE.txt
Requires-Dist: Pillow>=11.3; python_version >= "3.10"
Requires-Dist: Pillow==11.2.1; python_version <= "3.9"
Provides-Extra: develop
Requires-Dist: pytest; extra == "develop"
Requires-Dist: pre-commit; extra == "develop"
Dynamic: license-file
